greenscreen_control/__init__.py
greenscreen_control/chromecast_controller.py
greenscreen_control/common_args.py
greenscreen_control/greenscreen_client.py
greenscreen_control/greenscreen_control_cli.py
greenscreen_control/greenscreen_control_server.py
greenscreen_control/server.py
greenscreen_control-0.0.2.dist-info/DESCRIPTION.rst
greenscreen_control-0.0.2.dist-info/METADATA
greenscreen_control-0.0.2.dist-info/RECORD
greenscreen_control-0.0.2.dist-info/WHEEL
greenscreen_control-0.0.2.dist-info/entry_points.txt
greenscreen_control-0.0.2.dist-info/metadata.json
greenscreen_control-0.0.2.dist-info/top_level.txt
greenscreen_control-0.0.2.dist-info/zip-safe
