Metadata-Version: 2.0
Name: greenscreen-control
Version: 0.0.2
Summary: Python module, server and utility to control greenscreen.
Home-page: https://github.com/dermotduffy/greenscreen_control
Author: Dermot Duffy
Author-email: dermot.duffy@gmail.com
License: Apache Software License
Keywords: greenscreen chromecast cast
Platform: any
Classifier: Intended Audience :: Developers
Classifier: License :: OSI Approved :: Apache Software License
Classifier: Operating System :: OS Independent
Classifier: Programming Language :: Python
Classifier: Programming Language :: Python :: 2
Classifier: Programming Language :: Python :: 3
Classifier: Topic :: Home Automation
Classifier: Topic :: Software Development :: Libraries :: Python Modules
Requires-Dist: PyChromecast (>=0.8.1)
Requires-Dist: Twisted (>=16.0.0)
